Metadata-Version: 2.1
Name: typemallow
Version: 0.0.4
Summary: An elegant and automatic solution for generating/outputting Typescript interfaces from your Marshmallow Schemas.
Home-page: https://github.com/adenh93/typemallow
Author: Aden Herold
Author-email: aden.herold1@gmail.com
License: UNKNOWN
Keywords: Marshmallow,Typescript,Python,Flask,Django
Platform: any
